pycaroline/__init__.py
pycaroline/_version.py
pycaroline/cli.py
pycaroline/py.typed
pycaroline/validator.py
pycaroline/adapters/__init__.py
pycaroline/adapters/dataframe.py
pycaroline/comparison/__init__.py
pycaroline/comparison/comparator.py
pycaroline/comparison/models.py
pycaroline/config/__init__.py
pycaroline/config/loader.py
pycaroline/config/models.py
pycaroline/connectors/__init__.py
pycaroline/connectors/base.py
pycaroline/connectors/bigquery.py
pycaroline/connectors/factory.py
pycaroline/connectors/gcs.py
pycaroline/connectors/mysql.py
pycaroline/connectors/postgresql.py
pycaroline/connectors/redshift.py
pycaroline/connectors/s3.py
pycaroline/connectors/snowflake.py
pycaroline/loaders/__init__.py
pycaroline/loaders/api.py
pycaroline/loaders/exceptions.py
pycaroline/loaders/file_loader.py
pycaroline/loaders/models.py
pycaroline/reporting/__init__.py
pycaroline/reporting/generator.py
pycaroline-0.3.dist-info/METADATA
pycaroline-0.3.dist-info/WHEEL
pycaroline-0.3.dist-info/entry_points.txt
pycaroline-0.3.dist-info/licenses/LICENSE
pycaroline-0.3.dist-info/RECORD
