Metadata-Version: 2.4
Name: pycaroline
Version: 0.3
Summary: Data validation library for comparing tables across cloud data warehouses, cloud storage, and databases
Project-URL: Homepage, https://github.com/ryankarlos/pycaroline
Project-URL: Documentation, https://ryankarlos.github.io/pycaroline
Project-URL: Repository, https://github.com/ryankarlos/pycaroline.git
Project-URL: Issues, https://github.com/ryankarlos/pycaroline/issues
Project-URL: Changelog, https://github.com/ryankarlos/pycaroline/blob/main/CHANGELOG.md
Author-email: Ryan Nazareth <ryankarlos@gmail.com>
Maintainer-email: Ryan Nazareth <ryankarlos@gmail.com>
License: MIT
License-File: LICENSE
Keywords: bigquery,comparison,data,data-quality,datacompy,etl,gcs,migration,mysql,pandas,polars,postgresql,redshift,s3,snowflake,validation
Classifier: Development Status :: 4 - Beta
Classifier: Intended Audience :: Developers
Classifier: Intended Audience :: Science/Research
Classifier: License :: OSI Approved :: MIT License
Classifier: Operating System :: OS Independent
Classifier: Programming Language :: Python :: 3
Classifier: Programming Language :: Python :: 3.12
Classifier: Programming Language :: Python :: 3.13
Classifier: Topic :: Database
Classifier: Topic :: Software Development :: Libraries :: Python Modules
Classifier: Topic :: Software Development :: Quality Assurance
Classifier: Typing :: Typed
Requires-Python: >=3.12
Requires-Dist: click>=8.0.0
Requires-Dist: datacompy==0.19.1
Requires-Dist: polars>=1.0.0
Requires-Dist: pyyaml>=6.0
Provides-Extra: all
Requires-Dist: boto3>=1.26.0; extra == 'all'
Requires-Dist: gcsfs>=2023.1.0; extra == 'all'
Requires-Dist: google-cloud-bigquery>=3.0.0; extra == 'all'
Requires-Dist: google-cloud-storage>=2.0.0; extra == 'all'
Requires-Dist: mysql-connector-python>=8.0.0; extra == 'all'
Requires-Dist: pandas-gbq>=0.17.0; extra == 'all'
Requires-Dist: pandas>=2.0.0; extra == 'all'
Requires-Dist: psycopg2-binary>=2.9.0; extra == 'all'
Requires-Dist: redshift-connector>=2.0.0; extra == 'all'
Requires-Dist: s3fs>=2023.1.0; extra == 'all'
Requires-Dist: snowflake-connector-python>=3.0.0; extra == 'all'
Provides-Extra: bigquery
Requires-Dist: google-cloud-bigquery>=3.0.0; extra == 'bigquery'
Requires-Dist: pandas-gbq>=0.17.0; extra == 'bigquery'
Provides-Extra: dev
Requires-Dist: black>=24.0.0; extra == 'dev'
Requires-Dist: boto3>=1.26.0; extra == 'dev'
Requires-Dist: gcsfs>=2023.1.0; extra == 'dev'
Requires-Dist: google-cloud-bigquery>=3.0.0; extra == 'dev'
Requires-Dist: google-cloud-storage>=2.0.0; extra == 'dev'
Requires-Dist: hypothesis>=6.0.0; extra == 'dev'
Requires-Dist: mkdocs-jupyter>=0.24.0; extra == 'dev'
Requires-Dist: mkdocs-material>=9.0.0; extra == 'dev'
Requires-Dist: mkdocs>=1.5.0; extra == 'dev'
Requires-Dist: mkdocstrings[python]>=0.24.0; extra == 'dev'
Requires-Dist: mypy>=1.0.0; extra == 'dev'
Requires-Dist: mysql-connector-python>=8.0.0; extra == 'dev'
Requires-Dist: pandas-gbq>=0.17.0; extra == 'dev'
Requires-Dist: pandas>=2.0.0; extra == 'dev'
Requires-Dist: pre-commit>=3.0.0; extra == 'dev'
Requires-Dist: psycopg2-binary>=2.9.0; extra == 'dev'
Requires-Dist: pytest-cov>=4.0.0; extra == 'dev'
Requires-Dist: pytest-mock>=3.10.0; extra == 'dev'
Requires-Dist: pytest>=7.0.0; extra == 'dev'
Requires-Dist: redshift-connector>=2.0.0; extra == 'dev'
Requires-Dist: ruff>=0.1.0; extra == 'dev'
Requires-Dist: s3fs>=2023.1.0; extra == 'dev'
Requires-Dist: snowflake-connector-python>=3.0.0; extra == 'dev'
Requires-Dist: types-pyyaml>=6.0.0; extra == 'dev'
Provides-Extra: docs
Requires-Dist: mkdocs-jupyter>=0.24.0; extra == 'docs'
Requires-Dist: mkdocs-material>=9.0.0; extra == 'docs'
Requires-Dist: mkdocs>=1.5.0; extra == 'docs'
Requires-Dist: mkdocstrings[python]>=0.24.0; extra == 'docs'
Provides-Extra: gcs
Requires-Dist: gcsfs>=2023.1.0; extra == 'gcs'
Requires-Dist: google-cloud-storage>=2.0.0; extra == 'gcs'
Provides-Extra: mysql
Requires-Dist: mysql-connector-python>=8.0.0; extra == 'mysql'
Provides-Extra: pandas
Requires-Dist: pandas>=2.0.0; extra == 'pandas'
Provides-Extra: postgresql
Requires-Dist: psycopg2-binary>=2.9.0; extra == 'postgresql'
Provides-Extra: redshift
Requires-Dist: psycopg2-binary>=2.9.0; extra == 'redshift'
Requires-Dist: redshift-connector>=2.0.0; extra == 'redshift'
Provides-Extra: s3
Requires-Dist: boto3>=1.26.0; extra == 's3'
Requires-Dist: s3fs>=2023.1.0; extra == 's3'
Provides-Extra: snowflake
Requires-Dist: snowflake-connector-python>=3.0.0; extra == 'snowflake'
